purepyvmware/__init__.py
purepyvmware/base_connector.py
purepyvmware/datastores.py
purepyvmware/lib/__init__.py
purepyvmware/lib/datastore_utils.py
purepyvmware/lib/logging_utils.py
purepyvmware-1.0.0.dist-info/DESCRIPTION.rst
purepyvmware-1.0.0.dist-info/METADATA
purepyvmware-1.0.0.dist-info/RECORD
purepyvmware-1.0.0.dist-info/WHEEL
purepyvmware-1.0.0.dist-info/metadata.json
purepyvmware-1.0.0.dist-info/top_level.txt
