Metadata-Version: 2.0
Name: purepyvmware
Version: 1.0.0
Summary: Pure Storage Python SDK for FlashArray and VMware Integration
Home-page: https://github.com/PureStorage-OpenConnect/PureStorage-VMware-Python-SDK
Author: Jacob Hopkinson
Author-email: jhop@purestorage.com
License: Apache-2.0
Download-URL: https://github.com/PureStorage-OpenConnect/PureStorage-VMware-Python-SDK/archive/master.zip
Keywords: Pure Storage,Python,clients,REST,API,FlashArray,VMware
Platform: UNKNOWN
Requires-Python: >=3.6
Requires-Dist: purestorage (>=1.18.0)
Requires-Dist: pyvmomi (>=6.7.3)
